{
  "comments": [
    "(Just tried this on 3.2 M2 / I20050923-1000)\nReproduce steps:\n1. Right click on project -\u003e Export -\u003e Eclipse Product\n2. In Configuration field, type anything (I\u0027m partial to \"abc\")\n3. Click on Browse button and get IllegalArgumentException (stack trace below)\n\nError 2005-10-04 01:08:02.269 Path must include project and resource name: /.product\njava.lang.IllegalArgumentException: Path must include project and resource name:\n/.product\n\tat org.eclipse.core.internal.utils.Assert.isLegal(Assert.java:60)\n\tat org.eclipse.core.internal.resources.Workspace.newResource(Workspace.java:1560)\n\tat org.eclipse.core.internal.resources.Container.getFile(Container.java:125)\n\tat\norg.eclipse.pde.internal.ui.wizards.exports.ProductExportWizardPage.getProductFile(ProductExportWizardPage.java:271)\n\tat\norg.eclipse.pde.internal.ui.wizards.exports.ProductExportWizardPage.handleBrowse(ProductExportWizardPage.java:214)\n\tat\norg.eclipse.pde.internal.ui.wizards.exports.ProductExportWizardPage.access$0(ProductExportWizardPage.java:201)\n\tat\norg.eclipse.pde.internal.ui.wizards.exports.ProductExportWizardPage$1.widgetSelected(ProductExportWizardPage.java:116)\n\tat org.eclipse.swt.widgets.TypedListener.handleEvent(TypedListener.java:90)\n\tat org.eclipse.swt.widgets.EventTable.sendEvent(EventTable.java:66)\n\tat org.eclipse.swt.widgets.Widget.sendEvent(Widget.java:884)\n\tat org.eclipse.swt.widgets.Display.runDeferredEvents(Display.java:3194)\n\tat org.eclipse.swt.widgets.Display.readAndDispatch(Display.java:2823)\n\tat org.eclipse.jface.window.Window.runEventLoop(Window.java:809)\n\tat org.eclipse.jface.window.Window.open(Window.java:787)\n\tat org.eclipse.ui.actions.ExportResourcesAction.run(ExportResourcesAction.java:180)\n\tat\norg.eclipse.ui.actions.BaseSelectionListenerAction.runWithEvent(BaseSelectionListenerAction.java:167)\n\tat\norg.eclipse.jface.action.ActionContributionItem.handleWidgetSelection(ActionContributionItem.java:538)\n\tat\norg.eclipse.jface.action.ActionContributionItem.access$2(ActionContributionItem.java:488)\n\tat\norg.eclipse.jface.action.ActionContributionItem$5.handleEvent(ActionContributionItem.java:400)\n\tat org.eclipse.swt.widgets.EventTable.sendEvent(EventTable.java:66)\n\tat org.eclipse.swt.widgets.Widget.sendEvent(Widget.java:884)\n\tat org.eclipse.swt.widgets.Display.runDeferredEvents(Display.java:3194)\n\tat org.eclipse.swt.widgets.Display.readAndDispatch(Display.java:2823)\n\tat org.eclipse.ui.internal.Workbench.runEventLoop(Workbench.java:1755)\n\tat org.eclipse.ui.internal.Workbench.runUI(Workbench.java:1719)\n\tat org.eclipse.ui.internal.Workbench.createAndRunWorkbench(Workbench.java:368)\n\tat org.eclipse.ui.PlatformUI.createAndRunWorkbench(PlatformUI.java:143)\n\tat org.eclipse.ui.internal.ide.IDEApplication.run(IDEApplication.java:106)\n\tat\norg.eclipse.core.internal.runtime.PlatformActivator$1.run(PlatformActivator.java:226)\n\tat org.eclipse.core.runtime.adaptor.EclipseStarter.run(EclipseStarter.java:377)\n\tat org.eclipse.core.runtime.adaptor.EclipseStarter.run(EclipseStarter.java:164)\n\tat sun.reflect.NativeMethodAccessorImpl.invoke0(Native Method)\n\tat sun.reflect.NativeMethodAccessorImpl.invoke(Unknown Source)\n\tat sun.reflect.DelegatingMethodAccessorImpl.invoke(Unknown Source)\n\tat java.lang.reflect.Method.invoke(Unknown Source)\n\tat org.eclipse.core.launcher.Main.invokeFramework(Main.java:338)\n\tat org.eclipse.core.launcher.Main.basicRun(Main.java:282)\n\tat org.eclipse.core.launcher.Main.run(Main.java:977)\n\tat org.eclipse.core.launcher.Main.main(Main.java:952)",
    "Our friend Janek to the rescue!",
    "Oh oh!  Janek, the \"Configuration\" and \"Source Compatibility\" fields have the\nsame mnemonic.  Do you mind changing that too? :)\n\nSorry!",
    "Exception fixed and mnemonics updated :) "
  ],
  "commentCreationDates": [
    "2005-10-04T07:14:49+02:00",
    "2005-10-04T07:36:00+02:00",
    "2005-10-04T08:01:00+02:00",
    "2005-10-04T17:05:21+02:00"
  ],
  "traces": [
    {
      "exceptionType": "java.lang.IllegalArgumentException",
      "message": "Path must include project and resource name: /.product",
      "elements": [
        {
          "method": "org.eclipse.core.internal.utils.Assert.isLegal",
          "source": "Assert.java:60"
        },
        {
          "method": "org.eclipse.core.internal.resources.Workspace.newResource",
          "source": "Workspace.java:1560"
        },
        {
          "method": "org.eclipse.core.internal.resources.Container.getFile",
          "source": "Container.java:125"
        },
        {
          "method": "org.eclipse.pde.internal.ui.wizards.exports.ProductExportWizardPage.getProductFile",
          "source": "ProductExportWizardPage.java:271"
        },
        {
          "method": "org.eclipse.pde.internal.ui.wizards.exports.ProductExportWizardPage.handleBrowse",
          "source": "ProductExportWizardPage.java:214"
        },
        {
          "method": "org.eclipse.pde.internal.ui.wizards.exports.ProductExportWizardPage.access$0",
          "source": "ProductExportWizardPage.java:201"
        },
        {
          "method": "org.eclipse.pde.internal.ui.wizards.exports.ProductExportWizardPage$1.widgetSelected",
          "source": "ProductExportWizardPage.java:116"
        },
        {
          "method": "org.eclipse.swt.widgets.TypedListener.handleEvent",
          "source": "TypedListener.java:90"
        },
        {
          "method": "org.eclipse.swt.widgets.EventTable.sendEvent",
          "source": "EventTable.java:66"
        },
        {
          "method": "org.eclipse.swt.widgets.Widget.sendEvent",
          "source": "Widget.java:884"
        },
        {
          "method": "org.eclipse.swt.widgets.Display.runDeferredEvents",
          "source": "Display.java:3194"
        },
        {
          "method": "org.eclipse.swt.widgets.Display.readAndDispatch",
          "source": "Display.java:2823"
        },
        {
          "method": "org.eclipse.jface.window.Window.runEventLoop",
          "source": "Window.java:809"
        },
        {
          "method": "org.eclipse.jface.window.Window.open",
          "source": "Window.java:787"
        },
        {
          "method": "org.eclipse.ui.actions.ExportResourcesAction.run",
          "source": "ExportResourcesAction.java:180"
        },
        {
          "method": "org.eclipse.ui.actions.BaseSelectionListenerAction.runWithEvent",
          "source": "BaseSelectionListenerAction.java:167"
        },
        {
          "method": "org.eclipse.jface.action.ActionContributionItem.handleWidgetSelection",
          "source": "ActionContributionItem.java:538"
        },
        {
          "method": "org.eclipse.jface.action.ActionContributionItem.access$2",
          "source": "ActionContributionItem.java:488"
        },
        {
          "method": "org.eclipse.jface.action.ActionContributionItem$5.handleEvent",
          "source": "ActionContributionItem.java:400"
        },
        {
          "method": "org.eclipse.swt.widgets.EventTable.sendEvent",
          "source": "EventTable.java:66"
        },
        {
          "method": "org.eclipse.swt.widgets.Widget.sendEvent",
          "source": "Widget.java:884"
        },
        {
          "method": "org.eclipse.swt.widgets.Display.runDeferredEvents",
          "source": "Display.java:3194"
        },
        {
          "method": "org.eclipse.swt.widgets.Display.readAndDispatch",
          "source": "Display.java:2823"
        },
        {
          "method": "org.eclipse.ui.internal.Workbench.runEventLoop",
          "source": "Workbench.java:1755"
        },
        {
          "method": "org.eclipse.ui.internal.Workbench.runUI",
          "source": "Workbench.java:1719"
        },
        {
          "method": "org.eclipse.ui.internal.Workbench.createAndRunWorkbench",
          "source": "Workbench.java:368"
        },
        {
          "method": "org.eclipse.ui.PlatformUI.createAndRunWorkbench",
          "source": "PlatformUI.java:143"
        },
        {
          "method": "org.eclipse.ui.internal.ide.IDEApplication.run",
          "source": "IDEApplication.java:106"
        },
        {
          "method": "org.eclipse.core.internal.runtime.PlatformActivator$1.run",
          "source": "PlatformActivator.java:226"
        },
        {
          "method": "org.eclipse.core.runtime.adaptor.EclipseStarter.run",
          "source": "EclipseStarter.java:377"
        },
        {
          "method": "org.eclipse.core.runtime.adaptor.EclipseStarter.run",
          "source": "EclipseStarter.java:164"
        },
        {
          "method": "sun.reflect.NativeMethodAccessorImpl.invoke0",
          "source": "Native Method"
        },
        {
          "method": "sun.reflect.NativeMethodAccessorImpl.invoke",
          "source": "Unknown Source"
        },
        {
          "method": "sun.reflect.DelegatingMethodAccessorImpl.invoke",
          "source": "Unknown Source"
        },
        {
          "method": "java.lang.reflect.Method.invoke",
          "source": "Unknown Source"
        },
        {
          "method": "org.eclipse.core.launcher.Main.invokeFramework",
          "source": "Main.java:338"
        },
        {
          "method": "org.eclipse.core.launcher.Main.basicRun",
          "source": "Main.java:282"
        },
        {
          "method": "org.eclipse.core.launcher.Main.run",
          "source": "Main.java:977"
        },
        {
          "method": "org.eclipse.core.launcher.Main.main",
          "source": "Main.java:952"
        }
      ],
      "number": 0,
      "commentIndex": 0,
      "bugId": "111408",
      "date": "2005-10-04T07:14:49+02:00",
      "product": "PDE",
      "component": "UI",
      "severity": "normal"
    }
  ],
  "groupId": "111408",
  "bugId": "111408",
  "date": "2005-10-04T07:14:49+02:00",
  "product": "PDE",
  "component": "UI",
  "severity": "normal"
}