{
  "comments": [
    "We have failing test cases in JDT/UI in N20051027-0010 due to NPE in\norg.eclipse.swt.SWTException.\n\nFailed to execute runnable (java.lang.NullPointerException)\n\norg.eclipse.swt.SWTException: Failed to execute runnable\n(java.lang.NullPointerException)\nat org.eclipse.swt.SWT.error(SWT.java:3262)\nat org.eclipse.swt.SWT.error(SWT.java:3185)\nat org.eclipse.swt.widgets.Synchronizer.runAsyncMessages(Synchronizer.java:126)\nat org.eclipse.swt.widgets.Display.runAsyncMessages(Display.java:3117)\nat org.eclipse.swt.widgets.Display.readAndDispatch(Display.java:2902)\nat\norg.eclipse.jface.operation.ModalContext$ModalContextThread.block(ModalContext.java:153)\nat org.eclipse.jface.operation.ModalContext.run(ModalContext.java:303)\nat\norg.eclipse.jface.dialogs.ProgressMonitorDialog.run(ProgressMonitorDialog.java:453)\nat\norg.eclipse.ui.internal.progress.ProgressMonitorJobsDialog.run(ProgressMonitorJobsDialog.java:261)\nat org.eclipse.ui.internal.progress.ProgressManager$3.run(ProgressManager.java:866)\nat org.eclipse.swt.custom.BusyIndicator.showWhile(BusyIndicator.java:69)\nat\norg.eclipse.ui.internal.progress.ProgressManager.busyCursorWhile(ProgressManager.java:900)\nat\norg.eclipse.ui.internal.progress.ProgressManager.busyCursorWhile(ProgressManager.java:876)\nat\norg.eclipse.jdt.internal.junit.util.TestSearchEngine.findTests(TestSearchEngine.java:134)\nat\norg.eclipse.jdt.internal.junit.launcher.JUnitLaunchShortcut.launchType(JUnitLaunchShortcut.java:113)\nat\norg.eclipse.jdt.internal.junit.launcher.JUnitLaunchShortcut.searchAndLaunch(JUnitLaunchShortcut.java:103)\nat\norg.eclipse.jdt.internal.junit.launcher.JUnitLaunchShortcut.launch(JUnitLaunchShortcut.java:78)\nat\norg.eclipse.debug.internal.ui.launchConfigurations.LaunchShortcutExtension.launch(LaunchShortcutExtension.java:372)\nat\norg.eclipse.jdt.junit.tests.WrappingSystemTest.launchTests(WrappingSystemTest.java:169)\nat\norg.eclipse.jdt.junit.tests.WrappingSystemTest.runTests(WrappingSystemTest.java:118)\nat\norg.eclipse.jdt.junit.tests.WrappingSystemTest.test00characterizeSecondLine(WrappingSystemTest.java:64)\nat junit.extensions.TestDecorator.basicRun(TestDecorator.java:22)\nat junit.extensions.TestSetup$1.protect(TestSetup.java:19)\nat junit.extensions.TestSetup.run(TestSetup.java:23)\nat org.eclipse.test.EclipseTestRunner.run(EclipseTestRunner.java:330)\nat org.eclipse.test.EclipseTestRunner.run(EclipseTestRunner.java:204)\nat org.eclipse.test.UITestApplication$3.run(UITestApplication.java:188)\nat org.eclipse.swt.widgets.RunnableLock.run(RunnableLock.java:35)\nat org.eclipse.swt.widgets.Synchronizer.runAsyncMessages(Synchronizer.java:123)\nat org.eclipse.swt.widgets.Display.runAsyncMessages(Display.java:3117)\nat org.eclipse.swt.widgets.Display.readAndDispatch(Display.java:2894)\nat org.eclipse.ui.internal.Workbench.runEventLoop(Workbench.java:1763)\nat org.eclipse.ui.internal.Workbench.runUI(Workbench.java:1727)\nat org.eclipse.ui.internal.Workbench.createAndRunWorkbench(Workbench.java:371)\nat org.eclipse.ui.PlatformUI.createAndRunWorkbench(PlatformUI.java:143)\nat org.eclipse.ui.internal.ide.IDEApplication.run(IDEApplication.java:106)\nat org.eclipse.test.UITestApplication.runApplication(UITestApplication.java:131)\nat org.eclipse.test.UITestApplication.run(UITestApplication.java:58)\nat\norg.eclipse.core.internal.runtime.PlatformActivator$1.run(PlatformActivator.java:226)\nat org.eclipse.core.runtime.adaptor.EclipseStarter.run(EclipseStarter.java:386)\nat org.eclipse.core.runtime.adaptor.EclipseStarter.run(EclipseStarter.java:165)\nat org.eclipse.core.launcher.Main.invokeFramework(Main.java:338)\nat org.eclipse.core.launcher.Main.basicRun(Main.java:282)\nat org.eclipse.core.launcher.Main.run(Main.java:977)\nat org.eclipse.core.launcher.Main.main(Main.java:952)",
    "\n\n*** This bug has been marked as a duplicate of 113971 ***"
  ],
  "commentCreationDates": [
    "2005-10-27T21:00:54+02:00",
    "2005-10-27T21:07:15+02:00"
  ],
  "traces": [
    {
      "exceptionType": "org.eclipse.swt.SWTException",
      "message": "Failed to execute runnable (java.lang.NullPointerException)",
      "elements": [
        {
          "method": "org.eclipse.swt.SWT.error",
          "source": "SWT.java:3262"
        },
        {
          "method": "org.eclipse.swt.SWT.error",
          "source": "SWT.java:3185"
        },
        {
          "method": "org.eclipse.swt.widgets.Synchronizer.runAsyncMessages",
          "source": "Synchronizer.java:126"
        },
        {
          "method": "org.eclipse.swt.widgets.Display.runAsyncMessages",
          "source": "Display.java:3117"
        },
        {
          "method": "org.eclipse.swt.widgets.Display.readAndDispatch",
          "source": "Display.java:2902"
        },
        {
          "method": "org.eclipse.jface.operation.ModalContext$ModalContextThread.block",
          "source": "ModalContext.java:153"
        },
        {
          "method": "org.eclipse.jface.operation.ModalContext.run",
          "source": "ModalContext.java:303"
        },
        {
          "method": "org.eclipse.jface.dialogs.ProgressMonitorDialog.run",
          "source": "ProgressMonitorDialog.java:453"
        },
        {
          "method": "org.eclipse.ui.internal.progress.ProgressMonitorJobsDialog.run",
          "source": "ProgressMonitorJobsDialog.java:261"
        },
        {
          "method": "org.eclipse.ui.internal.progress.ProgressManager$3.run",
          "source": "ProgressManager.java:866"
        },
        {
          "method": "org.eclipse.swt.custom.BusyIndicator.showWhile",
          "source": "BusyIndicator.java:69"
        },
        {
          "method": "org.eclipse.ui.internal.progress.ProgressManager.busyCursorWhile",
          "source": "ProgressManager.java:900"
        },
        {
          "method": "org.eclipse.ui.internal.progress.ProgressManager.busyCursorWhile",
          "source": "ProgressManager.java:876"
        },
        {
          "method": "org.eclipse.jdt.internal.junit.util.TestSearchEngine.findTests",
          "source": "TestSearchEngine.java:134"
        },
        {
          "method": "org.eclipse.jdt.internal.junit.launcher.JUnitLaunchShortcut.launchType",
          "source": "JUnitLaunchShortcut.java:113"
        },
        {
          "method": "org.eclipse.jdt.internal.junit.launcher.JUnitLaunchShortcut.searchAndLaunch",
          "source": "JUnitLaunchShortcut.java:103"
        },
        {
          "method": "org.eclipse.jdt.internal.junit.launcher.JUnitLaunchShortcut.launch",
          "source": "JUnitLaunchShortcut.java:78"
        },
        {
          "method": "org.eclipse.debug.internal.ui.launchConfigurations.LaunchShortcutExtension.launch",
          "source": "LaunchShortcutExtension.java:372"
        },
        {
          "method": "org.eclipse.jdt.junit.tests.WrappingSystemTest.launchTests",
          "source": "WrappingSystemTest.java:169"
        },
        {
          "method": "org.eclipse.jdt.junit.tests.WrappingSystemTest.runTests",
          "source": "WrappingSystemTest.java:118"
        },
        {
          "method": "org.eclipse.jdt.junit.tests.WrappingSystemTest.test00characterizeSecondLine",
          "source": "WrappingSystemTest.java:64"
        },
        {
          "method": "junit.extensions.TestDecorator.basicRun",
          "source": "TestDecorator.java:22"
        },
        {
          "method": "junit.extensions.TestSetup$1.protect",
          "source": "TestSetup.java:19"
        },
        {
          "method": "junit.extensions.TestSetup.run",
          "source": "TestSetup.java:23"
        },
        {
          "method": "org.eclipse.test.EclipseTestRunner.run",
          "source": "EclipseTestRunner.java:330"
        },
        {
          "method": "org.eclipse.test.EclipseTestRunner.run",
          "source": "EclipseTestRunner.java:204"
        },
        {
          "method": "org.eclipse.test.UITestApplication$3.run",
          "source": "UITestApplication.java:188"
        },
        {
          "method": "org.eclipse.swt.widgets.RunnableLock.run",
          "source": "RunnableLock.java:35"
        },
        {
          "method": "org.eclipse.swt.widgets.Synchronizer.runAsyncMessages",
          "source": "Synchronizer.java:123"
        },
        {
          "method": "org.eclipse.swt.widgets.Display.runAsyncMessages",
          "source": "Display.java:3117"
        },
        {
          "method": "org.eclipse.swt.widgets.Display.readAndDispatch",
          "source": "Display.java:2894"
        },
        {
          "method": "org.eclipse.ui.internal.Workbench.runEventLoop",
          "source": "Workbench.java:1763"
        },
        {
          "method": "org.eclipse.ui.internal.Workbench.runUI",
          "source": "Workbench.java:1727"
        },
        {
          "method": "org.eclipse.ui.internal.Workbench.createAndRunWorkbench",
          "source": "Workbench.java:371"
        },
        {
          "method": "org.eclipse.ui.PlatformUI.createAndRunWorkbench",
          "source": "PlatformUI.java:143"
        },
        {
          "method": "org.eclipse.ui.internal.ide.IDEApplication.run",
          "source": "IDEApplication.java:106"
        },
        {
          "method": "org.eclipse.test.UITestApplication.runApplication",
          "source": "UITestApplication.java:131"
        },
        {
          "method": "org.eclipse.test.UITestApplication.run",
          "source": "UITestApplication.java:58"
        },
        {
          "method": "org.eclipse.core.internal.runtime.PlatformActivator$1.run",
          "source": "PlatformActivator.java:226"
        },
        {
          "method": "org.eclipse.core.runtime.adaptor.EclipseStarter.run",
          "source": "EclipseStarter.java:386"
        },
        {
          "method": "org.eclipse.core.runtime.adaptor.EclipseStarter.run",
          "source": "EclipseStarter.java:165"
        },
        {
          "method": "org.eclipse.core.launcher.Main.invokeFramework",
          "source": "Main.java:338"
        },
        {
          "method": "org.eclipse.core.launcher.Main.basicRun",
          "source": "Main.java:282"
        },
        {
          "method": "org.eclipse.core.launcher.Main.run",
          "source": "Main.java:977"
        },
        {
          "method": "org.eclipse.core.launcher.Main.main",
          "source": "Main.java:952"
        }
      ],
      "number": 0,
      "commentIndex": 0,
      "bugId": "114027",
      "duplicateId": "113971",
      "date": "2005-10-27T21:00:54+02:00",
      "product": "Platform",
      "component": "SWT",
      "severity": "normal"
    }
  ],
  "groupId": "113971",
  "bugId": "114027",
  "duplicateId": "113971",
  "date": "2005-10-27T21:00:54+02:00",
  "product": "Platform",
  "component": "SWT",
  "severity": "normal"
}