{
  "comments": [
    "If @DeclareParents is used to add an interface, the interface must either\n\n* not have a super-interface\n* if it does have a super-interface, then all the the methods of the super-interface must be re-declared in the sub-interface.\n\nIf an attempt is made to add an interface that has a parent, the target class will refer to a member field based on the name of the class that declared the method.  This causes methods that are not declared on the top level interface to fail due to a NoSuchFieldError.\n\nTest case attached will result in the following error...\n\nException in thread \"main\" java.lang.NoSuchFieldError: ajc$test_DeclareParentsAspect$test_A\n\tat test.TargetBad.doA(TargetBad.java:1)\n\tat test.Main.main(Main.java:21)\n\nAlso see TargetBad.jad",
    "Created an attachment (id\u003d53575)\ntest case that demonstrates the bug\n\nTo run test, the build.xml property ${aspectj.libs} must be set.\n"
  ],
  "commentCreationDates": [
    "2006-11-09T19:42:21+01:00",
    "2006-11-09T19:44:28+01:00"
  ],
  "traces": [
    {
      "exceptionType": "java.lang.NoSuchFieldError",
      "message": "ajc$test_DeclareParentsAspect$test_A",
      "elements": [
        {
          "method": "test.TargetBad.doA",
          "source": "TargetBad.java:1"
        },
        {
          "method": "test.Main.main",
          "source": "Main.java:21"
        }
      ],
      "number": 0,
      "commentIndex": 0,
      "bugId": "164016",
      "date": "2006-11-09T19:42:21+01:00",
      "product": "AspectJ",
      "component": "LTWeaving",
      "severity": "normal"
    }
  ],
  "groupId": "164016",
  "bugId": "164016",
  "date": "2006-11-09T19:42:21+01:00",
  "product": "AspectJ",
  "component": "LTWeaving",
  "severity": "normal"
}