{
  "comments": [
    "I20070418\nIf I recall correctly I got this error while changing the target platform.\njava.lang.NullPointerException\nat org.eclipse.pde.internal.core.SearchablePluginsManager.computeContainerClasspathEntries(SearchablePluginsManager.java:166)\nat org.eclipse.pde.internal.core.ExternalJavaSearchClasspathContainer.getClasspathEntries(ExternalJavaSearchClasspathContainer.java:29)\nat org.eclipse.jdt.internal.core.JavaProject.resolveClasspath(JavaProject.java:2579)\nat org.eclipse.jdt.internal.core.JavaProject.getResolvedClasspath(JavaProject.java:1863)\nat org.eclipse.jdt.internal.core.SetContainerOperation.executeOperation(SetContainerOperation.java:91)\nat org.eclipse.jdt.internal.core.JavaModelOperation.run(JavaModelOperation.java:720)\nat org.eclipse.core.internal.resources.Workspace.run(Workspace.java:1797)\nat org.eclipse.jdt.internal.core.JavaModelOperation.runOperation(JavaModelOperation.java:784)\nat org.eclipse.jdt.core.JavaCore.setClasspathContainer(JavaCore.java:4492)\nat org.eclipse.pde.internal.core.SearchablePluginsManager.resetContainer(SearchablePluginsManager.java:283)\nat org.eclipse.pde.internal.core.SearchablePluginsManager.modelsChanged(SearchablePluginsManager.java:295)\nat org.eclipse.pde.internal.core.PluginModelManager.fireDelta(PluginModelManager.java:250)\nat org.eclipse.pde.internal.core.PluginModelManager.modelsChanged(PluginModelManager.java:169)\nat org.eclipse.pde.internal.core.AbstractModelManager.fireModelProviderEvent(AbstractModelManager.java:34)\nat org.eclipse.pde.internal.ui.preferences.TargetPluginsTab.computeDelta(TargetPluginsTab.java:266)\nat org.eclipse.pde.internal.ui.preferences.TargetPluginsTab$5.run(TargetPluginsTab.java:672)\nat org.eclipse.swt.custom.BusyIndicator.showWhile(BusyIndicator.java:67)\nat org.eclipse.pde.internal.ui.preferences.TargetPluginsTab.performOk(TargetPluginsTab.java:654)\nat org.eclipse.pde.internal.ui.preferences.TargetPlatformPreferencePage.performOk(TargetPlatformPreferencePage.java:581)\nat org.eclipse.jface.preference.PreferenceDialog$12.run(PreferenceDialog.java:922)\nat org.eclipse.core.runtime.SafeRunner.run(SafeRunner.java:37)\nat org.eclipse.core.runtime.Platform.run(Platform.java:850)\nat org.eclipse.ui.internal.JFaceUtil$1.run(JFaceUtil.java:45)\nat org.eclipse.jface.util.SafeRunnable.run(SafeRunnable.java:187)\nat org.eclipse.jface.preference.PreferenceDialog.okPressed(PreferenceDialog.java:902)\nat org.eclipse.ui.internal.dialogs.FilteredPreferenceDialog.okPressed(FilteredPreferenceDialog.java:374)\nat org.eclipse.ui.internal.dialogs.WorkbenchPreferenceDialog.okPressed(WorkbenchPreferenceDialog.java:164)\nat org.eclipse.jface.preference.PreferenceDialog.buttonPressed(PreferenceDialog.java:230)\nat org.eclipse.jface.dialogs.Dialog$2.widgetSelected(Dialog.java:616)\nat org.eclipse.swt.widgets.TypedListener.handleEvent(TypedListener.java:227)\nat org.eclipse.swt.widgets.EventTable.sendEvent(EventTable.java:66)\nat org.eclipse.swt.widgets.Widget.sendEvent(Widget.java:938)\nat org.eclipse.swt.widgets.Display.runDeferredEvents(Display.java:3673)\nat org.eclipse.swt.widgets.Display.readAndDispatch(Display.java:3284)\nat org.eclipse.jface.window.Window.runEventLoop(Window.java:820)\nat org.eclipse.jface.window.Window.open(Window.java:796)\nat org.eclipse.ui.internal.OpenPreferencesAction.run(OpenPreferencesAction.java:65)\nat org.eclipse.jface.action.Action.runWithEvent(Action.java:498)\nat org.eclipse.jface.action.ActionContributionItem.handleWidgetSelection(ActionContributionItem.java:545)\nat org.eclipse.jface.action.ActionContributionItem.access$2(ActionContributionItem.java:490)\nat org.eclipse.jface.action.ActionContributionItem$5.handleEvent(ActionContributionItem.java:402)\nat org.eclipse.swt.widgets.EventTable.sendEvent(EventTable.java:66)\nat org.eclipse.swt.widgets.Widget.sendEvent(Widget.java:938)\nat org.eclipse.swt.widgets.Display.runDeferredEvents(Display.java:3673)\nat org.eclipse.swt.widgets.Display.readAndDispatch(Display.java:3284)\nat org.eclipse.ui.internal.Workbench.runEventLoop(Workbench.java:2365)\nat org.eclipse.ui.internal.Workbench.runUI(Workbench.java:2329)\nat org.eclipse.ui.internal.Workbench.access$4(Workbench.java:2204)\nat org.eclipse.ui.internal.Workbench$4.run(Workbench.java:466)\nat org.eclipse.core.databinding.observable.Realm.runWithDefault(Realm.java:289)\nat org.eclipse.ui.internal.Workbench.createAndRunWorkbench(Workbench.java:461)\nat org.eclipse.ui.PlatformUI.createAndRunWorkbench(PlatformUI.java:149)\nat org.eclipse.ui.internal.ide.application.IDEApplication.start(IDEApplication.java:101)\nat org.eclipse.equinox.internal.app.EclipseAppHandle.run(EclipseAppHandle.java:153)\nat org.eclipse.core.runtime.internal.adaptor.EclipseAppLauncher.runApplication(EclipseAppLauncher.java:106)\nat org.eclipse.core.runtime.internal.adaptor.EclipseAppLauncher.start(EclipseAppLauncher.java:76)\nat org.eclipse.core.runtime.adaptor.EclipseStarter.run(EclipseStarter.java:359)\nat org.eclipse.core.runtime.adaptor.EclipseStarter.run(EclipseStarter.java:174)\nat sun.reflect.NativeMethodAccessorImpl.invoke0(Native Method)\nat sun.reflect.NativeMethodAccessorImpl.invoke(Unknown Source)\nat sun.reflect.DelegatingMethodAccessorImpl.invoke(Unknown Source)\nat java.lang.reflect.Method.invoke(Unknown Source)\nat org.eclipse.equinox.launcher.Main.invokeFramework(Main.java:475)\nat org.eclipse.equinox.launcher.Main.basicRun(Main.java:415)\nat org.eclipse.equinox.launcher.Main.run(Main.java:1140)",
    "I also got it when restoring my workspace one it had crashed.",
    "\n\n*** This bug has been marked as a duplicate of bug 182961 ***"
  ],
  "commentCreationDates": [
    "2007-04-19T20:20:08+02:00",
    "2007-04-19T20:20:43+02:00",
    "2007-04-19T20:35:21+02:00"
  ],
  "traces": [
    {
      "exceptionType": "java.lang.NullPointerException",
      "elements": [
        {
          "method": "org.eclipse.pde.internal.core.SearchablePluginsManager.computeContainerClasspathEntries",
          "source": "SearchablePluginsManager.java:166"
        },
        {
          "method": "org.eclipse.pde.internal.core.ExternalJavaSearchClasspathContainer.getClasspathEntries",
          "source": "ExternalJavaSearchClasspathContainer.java:29"
        },
        {
          "method": "org.eclipse.jdt.internal.core.JavaProject.resolveClasspath",
          "source": "JavaProject.java:2579"
        },
        {
          "method": "org.eclipse.jdt.internal.core.JavaProject.getResolvedClasspath",
          "source": "JavaProject.java:1863"
        },
        {
          "method": "org.eclipse.jdt.internal.core.SetContainerOperation.executeOperation",
          "source": "SetContainerOperation.java:91"
        },
        {
          "method": "org.eclipse.jdt.internal.core.JavaModelOperation.run",
          "source": "JavaModelOperation.java:720"
        },
        {
          "method": "org.eclipse.core.internal.resources.Workspace.run",
          "source": "Workspace.java:1797"
        },
        {
          "method": "org.eclipse.jdt.internal.core.JavaModelOperation.runOperation",
          "source": "JavaModelOperation.java:784"
        },
        {
          "method": "org.eclipse.jdt.core.JavaCore.setClasspathContainer",
          "source": "JavaCore.java:4492"
        },
        {
          "method": "org.eclipse.pde.internal.core.SearchablePluginsManager.resetContainer",
          "source": "SearchablePluginsManager.java:283"
        },
        {
          "method": "org.eclipse.pde.internal.core.SearchablePluginsManager.modelsChanged",
          "source": "SearchablePluginsManager.java:295"
        },
        {
          "method": "org.eclipse.pde.internal.core.PluginModelManager.fireDelta",
          "source": "PluginModelManager.java:250"
        },
        {
          "method": "org.eclipse.pde.internal.core.PluginModelManager.modelsChanged",
          "source": "PluginModelManager.java:169"
        },
        {
          "method": "org.eclipse.pde.internal.core.AbstractModelManager.fireModelProviderEvent",
          "source": "AbstractModelManager.java:34"
        },
        {
          "method": "org.eclipse.pde.internal.ui.preferences.TargetPluginsTab.computeDelta",
          "source": "TargetPluginsTab.java:266"
        },
        {
          "method": "org.eclipse.pde.internal.ui.preferences.TargetPluginsTab$5.run",
          "source": "TargetPluginsTab.java:672"
        },
        {
          "method": "org.eclipse.swt.custom.BusyIndicator.showWhile",
          "source": "BusyIndicator.java:67"
        },
        {
          "method": "org.eclipse.pde.internal.ui.preferences.TargetPluginsTab.performOk",
          "source": "TargetPluginsTab.java:654"
        },
        {
          "method": "org.eclipse.pde.internal.ui.preferences.TargetPlatformPreferencePage.performOk",
          "source": "TargetPlatformPreferencePage.java:581"
        },
        {
          "method": "org.eclipse.jface.preference.PreferenceDialog$12.run",
          "source": "PreferenceDialog.java:922"
        },
        {
          "method": "org.eclipse.core.runtime.SafeRunner.run",
          "source": "SafeRunner.java:37"
        },
        {
          "method": "org.eclipse.core.runtime.Platform.run",
          "source": "Platform.java:850"
        },
        {
          "method": "org.eclipse.ui.internal.JFaceUtil$1.run",
          "source": "JFaceUtil.java:45"
        },
        {
          "method": "org.eclipse.jface.util.SafeRunnable.run",
          "source": "SafeRunnable.java:187"
        },
        {
          "method": "org.eclipse.jface.preference.PreferenceDialog.okPressed",
          "source": "PreferenceDialog.java:902"
        },
        {
          "method": "org.eclipse.ui.internal.dialogs.FilteredPreferenceDialog.okPressed",
          "source": "FilteredPreferenceDialog.java:374"
        },
        {
          "method": "org.eclipse.ui.internal.dialogs.WorkbenchPreferenceDialog.okPressed",
          "source": "WorkbenchPreferenceDialog.java:164"
        },
        {
          "method": "org.eclipse.jface.preference.PreferenceDialog.buttonPressed",
          "source": "PreferenceDialog.java:230"
        },
        {
          "method": "org.eclipse.jface.dialogs.Dialog$2.widgetSelected",
          "source": "Dialog.java:616"
        },
        {
          "method": "org.eclipse.swt.widgets.TypedListener.handleEvent",
          "source": "TypedListener.java:227"
        },
        {
          "method": "org.eclipse.swt.widgets.EventTable.sendEvent",
          "source": "EventTable.java:66"
        },
        {
          "method": "org.eclipse.swt.widgets.Widget.sendEvent",
          "source": "Widget.java:938"
        },
        {
          "method": "org.eclipse.swt.widgets.Display.runDeferredEvents",
          "source": "Display.java:3673"
        },
        {
          "method": "org.eclipse.swt.widgets.Display.readAndDispatch",
          "source": "Display.java:3284"
        },
        {
          "method": "org.eclipse.jface.window.Window.runEventLoop",
          "source": "Window.java:820"
        },
        {
          "method": "org.eclipse.jface.window.Window.open",
          "source": "Window.java:796"
        },
        {
          "method": "org.eclipse.ui.internal.OpenPreferencesAction.run",
          "source": "OpenPreferencesAction.java:65"
        },
        {
          "method": "org.eclipse.jface.action.Action.runWithEvent",
          "source": "Action.java:498"
        },
        {
          "method": "org.eclipse.jface.action.ActionContributionItem.handleWidgetSelection",
          "source": "ActionContributionItem.java:545"
        },
        {
          "method": "org.eclipse.jface.action.ActionContributionItem.access$2",
          "source": "ActionContributionItem.java:490"
        },
        {
          "method": "org.eclipse.jface.action.ActionContributionItem$5.handleEvent",
          "source": "ActionContributionItem.java:402"
        },
        {
          "method": "org.eclipse.swt.widgets.EventTable.sendEvent",
          "source": "EventTable.java:66"
        },
        {
          "method": "org.eclipse.swt.widgets.Widget.sendEvent",
          "source": "Widget.java:938"
        },
        {
          "method": "org.eclipse.swt.widgets.Display.runDeferredEvents",
          "source": "Display.java:3673"
        },
        {
          "method": "org.eclipse.swt.widgets.Display.readAndDispatch",
          "source": "Display.java:3284"
        },
        {
          "method": "org.eclipse.ui.internal.Workbench.runEventLoop",
          "source": "Workbench.java:2365"
        },
        {
          "method": "org.eclipse.ui.internal.Workbench.runUI",
          "source": "Workbench.java:2329"
        },
        {
          "method": "org.eclipse.ui.internal.Workbench.access$4",
          "source": "Workbench.java:2204"
        },
        {
          "method": "org.eclipse.ui.internal.Workbench$4.run",
          "source": "Workbench.java:466"
        },
        {
          "method": "org.eclipse.core.databinding.observable.Realm.runWithDefault",
          "source": "Realm.java:289"
        },
        {
          "method": "org.eclipse.ui.internal.Workbench.createAndRunWorkbench",
          "source": "Workbench.java:461"
        },
        {
          "method": "org.eclipse.ui.PlatformUI.createAndRunWorkbench",
          "source": "PlatformUI.java:149"
        },
        {
          "method": "org.eclipse.ui.internal.ide.application.IDEApplication.start",
          "source": "IDEApplication.java:101"
        },
        {
          "method": "org.eclipse.equinox.internal.app.EclipseAppHandle.run",
          "source": "EclipseAppHandle.java:153"
        },
        {
          "method": "org.eclipse.core.runtime.internal.adaptor.EclipseAppLauncher.runApplication",
          "source": "EclipseAppLauncher.java:106"
        },
        {
          "method": "org.eclipse.core.runtime.internal.adaptor.EclipseAppLauncher.start",
          "source": "EclipseAppLauncher.java:76"
        },
        {
          "method": "org.eclipse.core.runtime.adaptor.EclipseStarter.run",
          "source": "EclipseStarter.java:359"
        },
        {
          "method": "org.eclipse.core.runtime.adaptor.EclipseStarter.run",
          "source": "EclipseStarter.java:174"
        },
        {
          "method": "sun.reflect.NativeMethodAccessorImpl.invoke0",
          "source": "Native Method"
        },
        {
          "method": "sun.reflect.NativeMethodAccessorImpl.invoke",
          "source": "Unknown Source"
        },
        {
          "method": "sun.reflect.DelegatingMethodAccessorImpl.invoke",
          "source": "Unknown Source"
        },
        {
          "method": "java.lang.reflect.Method.invoke",
          "source": "Unknown Source"
        },
        {
          "method": "org.eclipse.equinox.launcher.Main.invokeFramework",
          "source": "Main.java:475"
        },
        {
          "method": "org.eclipse.equinox.launcher.Main.basicRun",
          "source": "Main.java:415"
        },
        {
          "method": "org.eclipse.equinox.launcher.Main.run",
          "source": "Main.java:1140"
        }
      ],
      "number": 0,
      "commentIndex": 0,
      "bugId": "183244",
      "duplicateId": "182961",
      "date": "2007-04-19T20:20:08+02:00",
      "product": "PDE",
      "component": "UI",
      "severity": "normal"
    }
  ],
  "groupId": "182961",
  "bugId": "183244",
  "duplicateId": "182961",
  "date": "2007-04-19T20:20:08+02:00",
  "product": "PDE",
  "component": "UI",
  "severity": "normal"
}