{
  "comments": [
    "if you use this in your workflow:\n\u003cprExcludes value\u003d\"*.xml, *.hbm\"/\u003e\n\nwithout setting \u003cprDefaultExcludes\u003e to false, this will cause an exception:\n\nINFO - Source scan started ...\nERROR - GlobbingFileFilter does not support stars in the middle (.svn*.xml,).\njava.lang.IllegalArgumentException: GlobbingFileFilter does not support stars in the middle (.svn*.xml,).\n\tat org.openarchitectureware.xpand2.pr.util.GenericFileFilter$GlobbingFileFilter.accept(GenericFileFilter.java:123)\n\tat org.openarchitectureware.xpand2.pr.util.GenericFileFilter.accept(GenericFileFilter.java:73)\n\tat org.openarchitectureware.xpand2.pr.util.GenericFileFilter.accept(GenericFileFilter.java:64)\n\tat java.io.File.listFiles(File.java:1091)\n\tat org.openarchitectureware.xpand2.pr.util.FSIO.getAllFilesInternal(FSIO.java:37)\n\tat org.openarchitectureware.xpand2.pr.util.FSIO.getAllFiles(FSIO.java:149)\n\tat org.openarchitectureware.xpand2.pr.ProtectedRegionResolverImpl.init(ProtectedRegionResolverImpl.java:307)\n\t\nworkaround:\nchanging to \u003cprExcludes value\u003d\", *.xml, *.hbm\"/\u003e\nwill fix it.\n\nbut it would be better to do this inside the code, because if you\u0027re setting \u003cprDefaultExcludes\u003e to false,\nthen \u003cprExcludes value\u003d\"*.xml, *.hbm\"/\u003e would be valid.\n\nor the lite version: add the different ways to the documentation ;-)"
  ],
  "commentCreationDates": [
    "2007-10-04T23:08:54+02:00"
  ],
  "traces": [
    {
      "exceptionType": "java.lang.IllegalArgumentException",
      "message": "GlobbingFileFilter does not support stars in the middle (.svn*.xml,).",
      "elements": [
        {
          "method": "org.openarchitectureware.xpand2.pr.util.GenericFileFilter$GlobbingFileFilter.accept",
          "source": "GenericFileFilter.java:123"
        },
        {
          "method": "org.openarchitectureware.xpand2.pr.util.GenericFileFilter.accept",
          "source": "GenericFileFilter.java:73"
        },
        {
          "method": "org.openarchitectureware.xpand2.pr.util.GenericFileFilter.accept",
          "source": "GenericFileFilter.java:64"
        },
        {
          "method": "java.io.File.listFiles",
          "source": "File.java:1091"
        },
        {
          "method": "org.openarchitectureware.xpand2.pr.util.FSIO.getAllFilesInternal",
          "source": "FSIO.java:37"
        },
        {
          "method": "org.openarchitectureware.xpand2.pr.util.FSIO.getAllFiles",
          "source": "FSIO.java:149"
        },
        {
          "method": "org.openarchitectureware.xpand2.pr.ProtectedRegionResolverImpl.init",
          "source": "ProtectedRegionResolverImpl.java:307"
        }
      ],
      "number": 0,
      "commentIndex": 0,
      "bugId": "205522",
      "date": "2007-10-04T23:08:54+02:00",
      "product": "GMT",
      "component": "oAW-workflow",
      "severity": "normal"
    }
  ],
  "groupId": "205522",
  "bugId": "205522",
  "date": "2007-10-04T23:08:54+02:00",
  "product": "GMT",
  "component": "oAW-workflow",
  "severity": "normal"
}