{
  "comments": [
    "plugin export 20030121\ni get this on scrolling\n\njava.lang.IllegalArgumentException: Argument cannot be null\n\tat org.eclipse.swt.SWT.error(SWT.java:2217)\n\tat org.eclipse.swt.SWT.error(SWT.java:2161)\n\tat org.eclipse.swt.graphics.GC.setForeground(GC.java:2068)\n\tat org.eclipse.jface.text.source.AnnotationPainter.draw\n(AnnotationPainter.java:351)\n\tat org.eclipse.jface.text.source.AnnotationPainter.handleDrawRequest\n(AnnotationPainter.java:270)\n\tat org.eclipse.jface.text.source.AnnotationPainter.paintControl\n(AnnotationPainter.java:233)\n\tat org.eclipse.swt.widgets.TypedListener.handleEvent\n(TypedListener.java:80)\n\tat org.eclipse.swt.widgets.EventTable.sendEvent(EventTable.java:77)\n\tat org.eclipse.swt.widgets.Widget.sendEvent(Widget.java:836)\n\tat org.eclipse.swt.widgets.Widget.sendEvent(Widget.java:861)\n\tat org.eclipse.swt.widgets.Widget.sendEvent(Widget.java:845)\n\tat org.eclipse.swt.widgets.Composite.WM_PAINT(Composite.java:726)\n\tat org.eclipse.swt.widgets.Control.windowProc(Control.java:2751)\n\tat org.eclipse.swt.widgets.Display.windowProc(Display.java:2177)\n\tat org.eclipse.swt.internal.win32.OS.DefWindowProcW(Native Method)\n\tat org.eclipse.swt.internal.win32.OS.DefWindowProc(OS.java:1287)\n\tat org.eclipse.swt.widgets.Scrollable.callWindowProc(Scrollable.java:73)\n\tat org.eclipse.swt.widgets.Composite.WM_SYSCOMMAND(Composite.java:816)\n\tat org.eclipse.swt.widgets.Control.windowProc(Control.java:2770)\n\tat org.eclipse.swt.widgets.Display.windowProc(Display.java:2177)\n\tat org.eclipse.swt.internal.win32.OS.DefWindowProcW(Native Method)\n\tat org.eclipse.swt.internal.win32.OS.DefWindowProc(OS.java:1287)\n\tat org.eclipse.swt.widgets.Scrollable.callWindowProc(Scrollable.java:73)\n\tat org.eclipse.swt.widgets.Control.windowProc(Control.java:2779)\n\tat org.eclipse.swt.widgets.Display.windowProc(Display.java:2177)\n\tat org.eclipse.swt.internal.win32.OS.DispatchMessageW(Native Method)\n\tat org.eclipse.swt.internal.win32.OS.DispatchMessage(OS.java:1292)\n\tat org.eclipse.swt.widgets.Display.readAndDispatch(Display.java:1408)\n\tat org.eclipse.ui.internal.Workbench.runEventLoop(Workbench.java:1467)\n\tat org.eclipse.ui.internal.Workbench.run(Workbench.java:1450)\n\tat org.eclipse.core.internal.boot.InternalBootLoader.run\n(InternalBootLoader.java:845)\n\tat org.eclipse.core.boot.BootLoader.run(BootLoader.java:462)\n\tat java.lang.reflect.Method.invoke(Native Method)\n\tat org.eclipse.core.launcher.Main.basicRun(Main.java:247)\n\tat org.eclipse.core.launcher.Main.run(Main.java:703)\n\tat org.eclipse.core.launcher.Main.main(Main.java:539)",
    "Build 20030121."
  ],
  "commentCreationDates": [
    "2003-01-21T11:22:37+01:00",
    "2003-01-21T14:29:22+01:00"
  ],
  "traces": [
    {
      "exceptionType": "java.lang.IllegalArgumentException",
      "message": "Argument cannot be null",
      "elements": [
        {
          "method": "org.eclipse.swt.SWT.error",
          "source": "SWT.java:2217"
        },
        {
          "method": "org.eclipse.swt.SWT.error",
          "source": "SWT.java:2161"
        },
        {
          "method": "org.eclipse.swt.graphics.GC.setForeground",
          "source": "GC.java:2068"
        },
        {
          "method": "org.eclipse.jface.text.source.AnnotationPainter.draw",
          "source": "AnnotationPainter.java:351"
        },
        {
          "method": "org.eclipse.jface.text.source.AnnotationPainter.handleDrawRequest",
          "source": "AnnotationPainter.java:270"
        },
        {
          "method": "org.eclipse.jface.text.source.AnnotationPainter.paintControl",
          "source": "AnnotationPainter.java:233"
        },
        {
          "method": "org.eclipse.swt.widgets.TypedListener.handleEvent",
          "source": "TypedListener.java:80"
        },
        {
          "method": "org.eclipse.swt.widgets.EventTable.sendEvent",
          "source": "EventTable.java:77"
        },
        {
          "method": "org.eclipse.swt.widgets.Widget.sendEvent",
          "source": "Widget.java:836"
        },
        {
          "method": "org.eclipse.swt.widgets.Widget.sendEvent",
          "source": "Widget.java:861"
        },
        {
          "method": "org.eclipse.swt.widgets.Widget.sendEvent",
          "source": "Widget.java:845"
        },
        {
          "method": "org.eclipse.swt.widgets.Composite.WM_PAINT",
          "source": "Composite.java:726"
        },
        {
          "method": "org.eclipse.swt.widgets.Control.windowProc",
          "source": "Control.java:2751"
        },
        {
          "method": "org.eclipse.swt.widgets.Display.windowProc",
          "source": "Display.java:2177"
        },
        {
          "method": "org.eclipse.swt.internal.win32.OS.DefWindowProcW",
          "source": "Native Method"
        },
        {
          "method": "org.eclipse.swt.internal.win32.OS.DefWindowProc",
          "source": "OS.java:1287"
        },
        {
          "method": "org.eclipse.swt.widgets.Scrollable.callWindowProc",
          "source": "Scrollable.java:73"
        },
        {
          "method": "org.eclipse.swt.widgets.Composite.WM_SYSCOMMAND",
          "source": "Composite.java:816"
        },
        {
          "method": "org.eclipse.swt.widgets.Control.windowProc",
          "source": "Control.java:2770"
        },
        {
          "method": "org.eclipse.swt.widgets.Display.windowProc",
          "source": "Display.java:2177"
        },
        {
          "method": "org.eclipse.swt.internal.win32.OS.DefWindowProcW",
          "source": "Native Method"
        },
        {
          "method": "org.eclipse.swt.internal.win32.OS.DefWindowProc",
          "source": "OS.java:1287"
        },
        {
          "method": "org.eclipse.swt.widgets.Scrollable.callWindowProc",
          "source": "Scrollable.java:73"
        },
        {
          "method": "org.eclipse.swt.widgets.Control.windowProc",
          "source": "Control.java:2779"
        },
        {
          "method": "org.eclipse.swt.widgets.Display.windowProc",
          "source": "Display.java:2177"
        },
        {
          "method": "org.eclipse.swt.internal.win32.OS.DispatchMessageW",
          "source": "Native Method"
        },
        {
          "method": "org.eclipse.swt.internal.win32.OS.DispatchMessage",
          "source": "OS.java:1292"
        },
        {
          "method": "org.eclipse.swt.widgets.Display.readAndDispatch",
          "source": "Display.java:1408"
        },
        {
          "method": "org.eclipse.ui.internal.Workbench.runEventLoop",
          "source": "Workbench.java:1467"
        },
        {
          "method": "org.eclipse.ui.internal.Workbench.run",
          "source": "Workbench.java:1450"
        },
        {
          "method": "org.eclipse.core.internal.boot.InternalBootLoader.run",
          "source": "InternalBootLoader.java:845"
        },
        {
          "method": "org.eclipse.core.boot.BootLoader.run",
          "source": "BootLoader.java:462"
        },
        {
          "method": "java.lang.reflect.Method.invoke",
          "source": "Native Method"
        },
        {
          "method": "org.eclipse.core.launcher.Main.basicRun",
          "source": "Main.java:247"
        },
        {
          "method": "org.eclipse.core.launcher.Main.run",
          "source": "Main.java:703"
        },
        {
          "method": "org.eclipse.core.launcher.Main.main",
          "source": "Main.java:539"
        }
      ],
      "number": 0,
      "commentIndex": 0,
      "bugId": "29874",
      "date": "2003-01-21T11:22:37+01:00",
      "product": "JDT",
      "component": "Text",
      "severity": "normal"
    }
  ],
  "groupId": "29874",
  "bugId": "29874",
  "date": "2003-01-21T11:22:37+01:00",
  "product": "JDT",
  "component": "Text",
  "severity": "normal"
}