{
  "comments": [
    "One of the debug views seems to be trying to recursively create itself. It seems\nto be trying to use WorkbenchPage.findView(WorkbenchPage.java:1455) to look up\nits own ID while its controls are still being created. The view won\u0027t be able to\nfind itself in the workbench page until it is fully initialized, so it almost\ncertainly isn\u0027t getting back the result it expects.\n\n(The workbench wasn\u0027t checking for this condition until recently).\n\n!ENTRY org.eclipse.ui 4 0 2005-03-11 19:55:24.449\n!MESSAGE Warning: Detected attempt by view org.eclipse.debug.ui.DebugView to\ncreate itself recursively (this is probably, but not necessarily, a bug)\n!STACK 1\norg.eclipse.ui.PartInitException: Warning: Detected attempt by view\norg.eclipse.debug.ui.DebugView to create itself recursively (this is probably,\nbut not necessarily, a bug)\n\tat org.eclipse.ui.internal.ViewFactory.busyRestoreView(ViewFactory.java:288)\n\tat org.eclipse.ui.internal.ViewFactory$1.run(ViewFactory.java:698)\n\tat org.eclipse.swt.custom.BusyIndicator.showWhile(BusyIndicator.java:69)\n\tat org.eclipse.ui.internal.ViewFactory.restoreView(ViewFactory.java:695)\n\tat org.eclipse.ui.internal.ViewFactory$ViewReference.getPart(ViewFactory.java:119)\n\tat org.eclipse.ui.internal.ViewFactory$ViewReference.getView(ViewFactory.java:172)\n\tat org.eclipse.ui.internal.WorkbenchPage.findView(WorkbenchPage.java:1455)\n\tat\norg.eclipse.debug.internal.ui.views.launch.LaunchView.createViewer(LaunchView.java:316)\n\tat\norg.eclipse.debug.ui.AbstractDebugView$ViewerPage.createControl(AbstractDebugView.java:254)\n\tat\norg.eclipse.debug.ui.AbstractDebugView.createDefaultPage(AbstractDebugView.java:342)\n\tat org.eclipse.ui.part.PageBookView.createPartControl(PageBookView.java:388)\n\tat\norg.eclipse.debug.ui.AbstractDebugView.createPartControl(AbstractDebugView.java:303)\n\tat org.eclipse.ui.internal.ViewFactory.busyRestoreViewHelper(ViewFactory.java:430)\n\tat org.eclipse.ui.internal.ViewFactory.busyRestoreView(ViewFactory.java:299)\n\tat org.eclipse.ui.internal.ViewFactory$1.run(ViewFactory.java:698)\n\tat org.eclipse.swt.custom.BusyIndicator.showWhile(BusyIndicator.java:69)\n\tat org.eclipse.ui.internal.ViewFactory.restoreView(ViewFactory.java:695)\n\tat org.eclipse.ui.internal.ViewFactory$ViewReference.getPart(ViewFactory.java:119)\n\tat org.eclipse.ui.internal.PartPane.setVisible(PartPane.java:260)\n\tat org.eclipse.ui.internal.ViewPane.setVisible(ViewPane.java:519)\n\tat\norg.eclipse.ui.internal.presentations.PresentablePart.setVisible(PresentablePart.java:126)\n\tat\norg.eclipse.ui.internal.presentations.newapi.PresentablePartFolder.select(PresentablePartFolder.java:268)\n\tat\norg.eclipse.ui.internal.presentations.newapi.LeftToRightTabOrder.select(LeftToRightTabOrder.java:65)\n\tat\norg.eclipse.ui.internal.presentations.newapi.TabbedStackPresentation.selectPart(TabbedStackPresentation.java:391)\n\tat\norg.eclipse.ui.internal.PartStack.refreshPresentationSelection(PartStack.java:1070)\n\tat org.eclipse.ui.internal.PartStack.createControl(PartStack.java:558)\n\tat org.eclipse.ui.internal.PartStack.createControl(PartStack.java:495)\n\tat\norg.eclipse.ui.internal.PartSashContainer.createControl(PartSashContainer.java:485)\n\tat org.eclipse.ui.internal.PerspectiveHelper.activate(PerspectiveHelper.java:230)\n\tat org.eclipse.ui.internal.Perspective.onActivate(Perspective.java:773)\n\tat org.eclipse.ui.internal.WorkbenchPage.setPerspective(WorkbenchPage.java:2819)\n\tat org.eclipse.ui.internal.WorkbenchPage.busySetPerspective(WorkbenchPage.java:843)\n\tat org.eclipse.ui.internal.WorkbenchPage.access$10(WorkbenchPage.java:828)\n\tat org.eclipse.ui.internal.WorkbenchPage$13.run(WorkbenchPage.java:2970)\n\tat org.eclipse.swt.custom.BusyIndicator.showWhile(BusyIndicator.java:69)\n\tat org.eclipse.ui.internal.WorkbenchPage.setPerspective(WorkbenchPage.java:2968)\n\tat\norg.eclipse.ui.internal.PerspectiveBarContributionItem.select(PerspectiveBarContributionItem.java:109)\n\tat\norg.eclipse.ui.internal.PerspectiveBarContributionItem$1.widgetSelected(PerspectiveBarContributionItem.java:81)\n\tat org.eclipse.swt.widgets.TypedListener.handleEvent(TypedListener.java:89)\n\tat org.eclipse.swt.widgets.EventTable.sendEvent(EventTable.java:82)\n\tat org.eclipse.swt.widgets.Widget.sendEvent(Widget.java:842)\n\tat org.eclipse.swt.widgets.Display.runDeferredEvents(Display.java:2894)\n\tat org.eclipse.swt.widgets.Display.readAndDispatch(Display.java:2527)\n\tat org.eclipse.ui.internal.Workbench.runEventLoop(Workbench.java:1514)\n\tat org.eclipse.ui.internal.Workbench.runUI(Workbench.java:1478)\n\tat org.eclipse.ui.internal.Workbench.createAndRunWorkbench(Workbench.java:297)\n\tat org.eclipse.ui.PlatformUI.createAndRunWorkbench(PlatformUI.java:143)\n\tat org.eclipse.ui.internal.ide.IDEApplication.run(IDEApplication.java:103)\n\tat\norg.eclipse.core.internal.runtime.PlatformActivator$1.run(PlatformActivator.java:228)\n\tat org.eclipse.core.runtime.adaptor.EclipseStarter.run(EclipseStarter.java:338)\n\tat org.eclipse.core.runtime.adaptor.EclipseStarter.run(EclipseStarter.java:151)\n\tat sun.reflect.NativeMethodAccessorImpl.invoke0(Native Method)\n\tat sun.reflect.NativeMethodAccessorImpl.invoke(NativeMethodAccessorImpl.java:39)\n\tat\nsun.reflect.DelegatingMethodAccessorImpl.invoke(DelegatingMethodAccessorImpl.java:25)\n\tat java.lang.reflect.Method.invoke(Method.java:324)\n\tat org.eclipse.core.launcher.Main.invokeFramework(Main.java:268)\n\tat org.eclipse.core.launcher.Main.basicRun(Main.java:260)\n\tat org.eclipse.core.launcher.Main.run(Main.java:887)\n\tat org.eclipse.core.launcher.Main.main(Main.java:871)",
    "\n\n*** This bug has been marked as a duplicate of 87955 ***"
  ],
  "commentCreationDates": [
    "2005-03-24T23:00:07+01:00",
    "2005-03-25T03:31:36+01:00"
  ],
  "traces": [
    {
      "exceptionType": "org.eclipse.ui.PartInitException",
      "message": "Warning: Detected attempt by view org.eclipse.debug.ui.DebugView to create itself recursively (this is probably, but not necessarily, a bug)",
      "elements": [
        {
          "method": "org.eclipse.ui.internal.ViewFactory.busyRestoreView",
          "source": "ViewFactory.java:288"
        },
        {
          "method": "org.eclipse.ui.internal.ViewFactory$1.run",
          "source": "ViewFactory.java:698"
        },
        {
          "method": "org.eclipse.swt.custom.BusyIndicator.showWhile",
          "source": "BusyIndicator.java:69"
        },
        {
          "method": "org.eclipse.ui.internal.ViewFactory.restoreView",
          "source": "ViewFactory.java:695"
        },
        {
          "method": "org.eclipse.ui.internal.ViewFactory$ViewReference.getPart",
          "source": "ViewFactory.java:119"
        },
        {
          "method": "org.eclipse.ui.internal.ViewFactory$ViewReference.getView",
          "source": "ViewFactory.java:172"
        },
        {
          "method": "org.eclipse.ui.internal.WorkbenchPage.findView",
          "source": "WorkbenchPage.java:1455"
        },
        {
          "method": "org.eclipse.debug.internal.ui.views.launch.LaunchView.createViewer",
          "source": "LaunchView.java:316"
        },
        {
          "method": "org.eclipse.debug.ui.AbstractDebugView$ViewerPage.createControl",
          "source": "AbstractDebugView.java:254"
        },
        {
          "method": "org.eclipse.debug.ui.AbstractDebugView.createDefaultPage",
          "source": "AbstractDebugView.java:342"
        },
        {
          "method": "org.eclipse.ui.part.PageBookView.createPartControl",
          "source": "PageBookView.java:388"
        },
        {
          "method": "org.eclipse.debug.ui.AbstractDebugView.createPartControl",
          "source": "AbstractDebugView.java:303"
        },
        {
          "method": "org.eclipse.ui.internal.ViewFactory.busyRestoreViewHelper",
          "source": "ViewFactory.java:430"
        },
        {
          "method": "org.eclipse.ui.internal.ViewFactory.busyRestoreView",
          "source": "ViewFactory.java:299"
        },
        {
          "method": "org.eclipse.ui.internal.ViewFactory$1.run",
          "source": "ViewFactory.java:698"
        },
        {
          "method": "org.eclipse.swt.custom.BusyIndicator.showWhile",
          "source": "BusyIndicator.java:69"
        },
        {
          "method": "org.eclipse.ui.internal.ViewFactory.restoreView",
          "source": "ViewFactory.java:695"
        },
        {
          "method": "org.eclipse.ui.internal.ViewFactory$ViewReference.getPart",
          "source": "ViewFactory.java:119"
        },
        {
          "method": "org.eclipse.ui.internal.PartPane.setVisible",
          "source": "PartPane.java:260"
        },
        {
          "method": "org.eclipse.ui.internal.ViewPane.setVisible",
          "source": "ViewPane.java:519"
        },
        {
          "method": "org.eclipse.ui.internal.presentations.PresentablePart.setVisible",
          "source": "PresentablePart.java:126"
        },
        {
          "method": "org.eclipse.ui.internal.presentations.newapi.PresentablePartFolder.select",
          "source": "PresentablePartFolder.java:268"
        },
        {
          "method": "org.eclipse.ui.internal.presentations.newapi.LeftToRightTabOrder.select",
          "source": "LeftToRightTabOrder.java:65"
        },
        {
          "method": "org.eclipse.ui.internal.presentations.newapi.TabbedStackPresentation.selectPart",
          "source": "TabbedStackPresentation.java:391"
        },
        {
          "method": "org.eclipse.ui.internal.PartStack.refreshPresentationSelection",
          "source": "PartStack.java:1070"
        },
        {
          "method": "org.eclipse.ui.internal.PartStack.createControl",
          "source": "PartStack.java:558"
        },
        {
          "method": "org.eclipse.ui.internal.PartStack.createControl",
          "source": "PartStack.java:495"
        },
        {
          "method": "org.eclipse.ui.internal.PartSashContainer.createControl",
          "source": "PartSashContainer.java:485"
        },
        {
          "method": "org.eclipse.ui.internal.PerspectiveHelper.activate",
          "source": "PerspectiveHelper.java:230"
        },
        {
          "method": "org.eclipse.ui.internal.Perspective.onActivate",
          "source": "Perspective.java:773"
        },
        {
          "method": "org.eclipse.ui.internal.WorkbenchPage.setPerspective",
          "source": "WorkbenchPage.java:2819"
        },
        {
          "method": "org.eclipse.ui.internal.WorkbenchPage.busySetPerspective",
          "source": "WorkbenchPage.java:843"
        },
        {
          "method": "org.eclipse.ui.internal.WorkbenchPage.access$10",
          "source": "WorkbenchPage.java:828"
        },
        {
          "method": "org.eclipse.ui.internal.WorkbenchPage$13.run",
          "source": "WorkbenchPage.java:2970"
        },
        {
          "method": "org.eclipse.swt.custom.BusyIndicator.showWhile",
          "source": "BusyIndicator.java:69"
        },
        {
          "method": "org.eclipse.ui.internal.WorkbenchPage.setPerspective",
          "source": "WorkbenchPage.java:2968"
        },
        {
          "method": "org.eclipse.ui.internal.PerspectiveBarContributionItem.select",
          "source": "PerspectiveBarContributionItem.java:109"
        },
        {
          "method": "org.eclipse.ui.internal.PerspectiveBarContributionItem$1.widgetSelected",
          "source": "PerspectiveBarContributionItem.java:81"
        },
        {
          "method": "org.eclipse.swt.widgets.TypedListener.handleEvent",
          "source": "TypedListener.java:89"
        },
        {
          "method": "org.eclipse.swt.widgets.EventTable.sendEvent",
          "source": "EventTable.java:82"
        },
        {
          "method": "org.eclipse.swt.widgets.Widget.sendEvent",
          "source": "Widget.java:842"
        },
        {
          "method": "org.eclipse.swt.widgets.Display.runDeferredEvents",
          "source": "Display.java:2894"
        },
        {
          "method": "org.eclipse.swt.widgets.Display.readAndDispatch",
          "source": "Display.java:2527"
        },
        {
          "method": "org.eclipse.ui.internal.Workbench.runEventLoop",
          "source": "Workbench.java:1514"
        },
        {
          "method": "org.eclipse.ui.internal.Workbench.runUI",
          "source": "Workbench.java:1478"
        },
        {
          "method": "org.eclipse.ui.internal.Workbench.createAndRunWorkbench",
          "source": "Workbench.java:297"
        },
        {
          "method": "org.eclipse.ui.PlatformUI.createAndRunWorkbench",
          "source": "PlatformUI.java:143"
        },
        {
          "method": "org.eclipse.ui.internal.ide.IDEApplication.run",
          "source": "IDEApplication.java:103"
        },
        {
          "method": "org.eclipse.core.internal.runtime.PlatformActivator$1.run",
          "source": "PlatformActivator.java:228"
        },
        {
          "method": "org.eclipse.core.runtime.adaptor.EclipseStarter.run",
          "source": "EclipseStarter.java:338"
        },
        {
          "method": "org.eclipse.core.runtime.adaptor.EclipseStarter.run",
          "source": "EclipseStarter.java:151"
        },
        {
          "method": "sun.reflect.NativeMethodAccessorImpl.invoke0",
          "source": "Native Method"
        },
        {
          "method": "sun.reflect.NativeMethodAccessorImpl.invoke",
          "source": "NativeMethodAccessorImpl.java:39"
        },
        {
          "method": "sun.reflect.DelegatingMethodAccessorImpl.invoke",
          "source": "DelegatingMethodAccessorImpl.java:25"
        },
        {
          "method": "java.lang.reflect.Method.invoke",
          "source": "Method.java:324"
        },
        {
          "method": "org.eclipse.core.launcher.Main.invokeFramework",
          "source": "Main.java:268"
        },
        {
          "method": "org.eclipse.core.launcher.Main.basicRun",
          "source": "Main.java:260"
        },
        {
          "method": "org.eclipse.core.launcher.Main.run",
          "source": "Main.java:887"
        },
        {
          "method": "org.eclipse.core.launcher.Main.main",
          "source": "Main.java:871"
        }
      ],
      "number": 0,
      "commentIndex": 0,
      "bugId": "89060",
      "duplicateId": "87955",
      "date": "2005-03-24T23:00:07+01:00",
      "product": "JDT",
      "component": "Debug",
      "severity": "normal"
    }
  ],
  "groupId": "87955",
  "bugId": "89060",
  "duplicateId": "87955",
  "date": "2005-03-24T23:00:07+01:00",
  "product": "JDT",
  "component": "Debug",
  "severity": "normal"
}