{
  "comments": [
    "Build: I20050509-1200\n\nI got this NPE several times when opening a manifest editor. I have not been\nable to reproduce the error, and after closing and reopening the editor, there\ndo not appear to be any other side-effects. Full log attached.\n\njava.lang.NullPointerException\n\tat org.eclipse.ui.forms.editor.FormEditor.isDirty(FormEditor.java:262)\n\tat\norg.eclipse.pde.internal.ui.editor.PDEFormEditor.computeDirtyState(PDEFormEditor.java:437)\n\tat org.eclipse.pde.internal.ui.editor.PDEFormEditor.isDirty(PDEFormEditor.java:427)\n\tat\norg.eclipse.pde.internal.ui.editor.PDEFormEditorContributor$SaveAction.update(PDEFormEditorContributor.java:105)\n\tat\norg.eclipse.pde.internal.ui.editor.PDEFormEditorContributor.updateActions(PDEFormEditorContributor.java:297)\n\tat\norg.eclipse.pde.internal.ui.editor.PDEFormEditor.editorDirtyStateChanged(PDEFormEditor.java:461)\n\tat\norg.eclipse.pde.internal.ui.editor.PDEFormEditor.fireSaveNeeded(PDEFormEditor.java:453)\n\tat\norg.eclipse.pde.internal.ui.editor.PDESourcePage.firePropertyChange(PDESourcePage.java:224)\n\tat\norg.eclipse.ui.texteditor.AbstractTextEditor.initializeTitle(AbstractTextEditor.java:2923)\n\tat\norg.eclipse.ui.texteditor.AbstractTextEditor.doSetInput(AbstractTextEditor.java:3010)\n\tat org.eclipse.ui.texteditor.StatusTextEditor.doSetInput(StatusTextEditor.java:173)\n\tat\norg.eclipse.ui.texteditor.AbstractDecoratedTextEditor.doSetInput(AbstractDecoratedTextEditor.java:1263)\n\tat org.eclipse.ui.editors.text.TextEditor.doSetInput(TextEditor.java:262)",
    "Created an attachment (id\u003d20845)\nLog file\n",
    "This is interesting. The field in question is initialized right in the \ndeclaration, so it is troubling that it can be null at any point. I added the \ncheck for null in \u0027isDirty\u0027 but I am still puzzled.",
    "The dispose() method makes the field null..."
  ],
  "commentCreationDates": [
    "2005-05-09T20:33:12+02:00",
    "2005-05-09T20:33:36+02:00",
    "2005-05-09T21:14:09+02:00",
    "2005-05-09T21:20:39+02:00"
  ],
  "traces": [
    {
      "exceptionType": "java.lang.NullPointerException",
      "elements": [
        {
          "method": "org.eclipse.ui.forms.editor.FormEditor.isDirty",
          "source": "FormEditor.java:262"
        },
        {
          "method": "org.eclipse.pde.internal.ui.editor.PDEFormEditor.computeDirtyState",
          "source": "PDEFormEditor.java:437"
        },
        {
          "method": "org.eclipse.pde.internal.ui.editor.PDEFormEditor.isDirty",
          "source": "PDEFormEditor.java:427"
        },
        {
          "method": "org.eclipse.pde.internal.ui.editor.PDEFormEditorContributor$SaveAction.update",
          "source": "PDEFormEditorContributor.java:105"
        },
        {
          "method": "org.eclipse.pde.internal.ui.editor.PDEFormEditorContributor.updateActions",
          "source": "PDEFormEditorContributor.java:297"
        },
        {
          "method": "org.eclipse.pde.internal.ui.editor.PDEFormEditor.editorDirtyStateChanged",
          "source": "PDEFormEditor.java:461"
        },
        {
          "method": "org.eclipse.pde.internal.ui.editor.PDEFormEditor.fireSaveNeeded",
          "source": "PDEFormEditor.java:453"
        },
        {
          "method": "org.eclipse.pde.internal.ui.editor.PDESourcePage.firePropertyChange",
          "source": "PDESourcePage.java:224"
        },
        {
          "method": "org.eclipse.ui.texteditor.AbstractTextEditor.initializeTitle",
          "source": "AbstractTextEditor.java:2923"
        },
        {
          "method": "org.eclipse.ui.texteditor.AbstractTextEditor.doSetInput",
          "source": "AbstractTextEditor.java:3010"
        },
        {
          "method": "org.eclipse.ui.texteditor.StatusTextEditor.doSetInput",
          "source": "StatusTextEditor.java:173"
        },
        {
          "method": "org.eclipse.ui.texteditor.AbstractDecoratedTextEditor.doSetInput",
          "source": "AbstractDecoratedTextEditor.java:1263"
        },
        {
          "method": "org.eclipse.ui.editors.text.TextEditor.doSetInput",
          "source": "TextEditor.java:262"
        }
      ],
      "number": 0,
      "commentIndex": 0,
      "bugId": "94172",
      "date": "2005-05-09T20:33:12+02:00",
      "product": "Platform",
      "component": "UI",
      "severity": "normal"
    }
  ],
  "groupId": "94172",
  "bugId": "94172",
  "date": "2005-05-09T20:33:12+02:00",
  "product": "Platform",
  "component": "UI",
  "severity": "normal"
}